zarrzipan/__init__.py
zarrzipan/__version__.py
zarrzipan/cli.py
zarrzipan/py.typed
zarrzipan/types.py
zarrzipan/zarrzipan.py
zarrzipan-0.1.0.dist-info/METADATA
zarrzipan-0.1.0.dist-info/WHEEL
zarrzipan-0.1.0.dist-info/entry_points.txt
zarrzipan-0.1.0.dist-info/licenses/LICENSE
zarrzipan-0.1.0.dist-info/RECORD
