Metadata-Version: 2.4
Name: zarrzipan
Version: 0.1.0
Summary: A zarr-based compression benchmarking tool
Project-URL: Repository, https://github.com/jkeifer/zarrzipan
Author-email: Jarrett Keifer <jkeifer0@gmail.com>
License: Apache License 2.0
License-File: LICENSE
Requires-Python: >=3.12
Requires-Dist: numcodecs>=0.16.0
Requires-Dist: numpy>=2.2.5
Requires-Dist: zarr>=3.0.7
